mysql_context_manager/__init__.py
mysql_context_manager-0.3.0.dist-info/LICENSE
mysql_context_manager-0.3.0.dist-info/METADATA
mysql_context_manager-0.3.0.dist-info/WHEEL
mysql_context_manager-0.3.0.dist-info/RECORD
