Metadata-Version: 2.3
Name: mysql-context-manager
Version: 0.3.0
Summary: Work with MySQL databases asynchronously, and in context.
License: MIT
Author: IdoKendo
Author-email: ryuusuke@gmail.com
Requires-Python: >=3.9,<4.0
Classifier: License :: OSI Approved :: MIT License
Classifier: Programming Language :: Python :: 3
Classifier: Programming Language :: Python :: 3.9
Classifier: Programming Language :: Python :: 3.10
Classifier: Programming Language :: Python :: 3.11
Classifier: Programming Language :: Python :: 3.12
Classifier: Programming Language :: Python :: 3.13
Requires-Dist: PyMySQL (>=1.1,<2.0)
Requires-Dist: aiomysql (>=0.2,<0.3)
Requires-Dist: databases (>=0.9,<0.10)
Project-URL: Homepage, https://pypi.org/project/mysql-context-manager/
Project-URL: Repository, https://github.com/IdoKendo/mysql-context-manager
